mediumroast_py/__init__.py
mediumroast_py/api/__init__.py
mediumroast_py/api/authorize.py
mediumroast_py/api/github.py
mediumroast_py/api/github_server.py
mediumroast_py/api/messages.json
mediumroast_py-0.6.15.0.dist-info/LICENSE
mediumroast_py-0.6.15.0.dist-info/METADATA
mediumroast_py-0.6.15.0.dist-info/WHEEL
mediumroast_py-0.6.15.0.dist-info/entry_points.txt
mediumroast_py-0.6.15.0.dist-info/RECORD
