Metadata-Version: 2.3
Name: mediumroast_py
Version: 0.6.15.0
Summary: This Python package provides a Software Development Kit (SDK) for interacting with Mediumroast for GitHub. It is used internally by Mediumroast, Inc. and meant for developers to make use of.
License: Apache-2.0
Keywords: Product Management,Competitive Insights,Customer Insights,Partner Insights,Empowered Teams
Author: Michael Hay
Author-email: michael.hay@mediumroast.io
Requires-Python: >=3.8,<4.0
Classifier: License :: OSI Approved :: Apache Software License
Classifier: Programming Language :: Python :: 3
Classifier: Programming Language :: Python :: 3.8
Classifier: Programming Language :: Python :: 3.9
Classifier: Programming Language :: Python :: 3.10
Classifier: Programming Language :: Python :: 3.11
Classifier: Programming Language :: Python :: 3.12
Classifier: Programming Language :: Python :: 3.13
Requires-Dist: cryptography (>=42.0.6,<43.0.0)
Requires-Dist: pygithub (>=2.3.0,<3.0.0)
Requires-Dist: pyjwt (>=2.8.0,<3.0.0)
Requires-Dist: python-dotenv (>=1.0.1,<2.0.0)
Requires-Dist: requests (>=2.28.1,<3.0.0)
Project-URL: Bug Tracker, https://github.com/mediumroast/mediumroast_py/issues
Project-URL: Repository, https://github.com/mediumroast/mediumroast_py
